{
  "version": "1.0",
  "ctrl_pkt_patch_info": [
    {
      "offset": 5820,
      "size": 6,
      "xrt_arg_idx": 3,
      "bo_offset": 0
    },
    {
      "offset": 5868,
      "size": 6,
      "xrt_arg_idx": 2,
      "bo_offset": 0
    },
    {
      "offset": 5916,
      "size": 6,
      "xrt_arg_idx": 1,
      "bo_offset": 0
    },
    {
      "offset": 5964,
      "size": 6,
      "xrt_arg_idx": 1,
      "bo_offset": 98304
    },
    {
      "offset": 6012,
      "size": 6,
      "xrt_arg_idx": 0,
      "bo_offset": 0
    },
    {
      "offset": 6132,
      "size": 6,
      "xrt_arg_idx": 3,
      "bo_offset": 0
    },
    {
      "offset": 6180,
      "size": 6,
      "xrt_arg_idx": 2,
      "bo_offset": 0
    },
    {
      "offset": 6228,
      "size": 6,
      "xrt_arg_idx": 1,
      "bo_offset": 384
    },
    {
      "offset": 6276,
      "size": 6,
      "xrt_arg_idx": 1,
      "bo_offset": 98304
    },
    {
      "offset": 6324,
      "size": 6,
      "xrt_arg_idx": 0,
      "bo_offset": 384
    },
    {
      "offset": 6444,
      "size": 6,
      "xrt_arg_idx": 3,
      "bo_offset": 0
    },
    {
      "offset": 6492,
      "size": 6,
      "xrt_arg_idx": 2,
      "bo_offset": 0
    },
    {
      "offset": 6540,
      "size": 6,
      "xrt_arg_idx": 1,
      "bo_offset": 768
    },
    {
      "offset": 6588,
      "size": 6,
      "xrt_arg_idx": 1,
      "bo_offset": 98304
    },
    {
      "offset": 6636,
      "size": 6,
      "xrt_arg_idx": 0,
      "bo_offset": 768
    },
    {
      "offset": 6756,
      "size": 6,
      "xrt_arg_idx": 3,
      "bo_offset": 0
    },
    {
      "offset": 6804,
      "size": 6,
      "xrt_arg_idx": 2,
      "bo_offset": 0
    },
    {
      "offset": 6852,
      "size": 6,
      "xrt_arg_idx": 1,
      "bo_offset": 1152
    },
    {
      "offset": 6900,
      "size": 6,
      "xrt_arg_idx": 1,
      "bo_offset": 98304
    },
    {
      "offset": 6948,
      "size": 6,
      "xrt_arg_idx": 0,
      "bo_offset": 1152
    }
  ]
}
